PyJsonFriendly/__init__.py
PyJsonFriendly/_version.py
PyJsonFriendly/jsonfriendly.py
PyJsonFriendly/JsonFriendlyNumpyNDArray/__init__.py
tests/__init__.py
tests/test_JsonFriendlyNumpyNDArray.py
tests/test_pyJsonFriendly.py
PyJsonFriendly-19.11.0.dist-info/LICENSE
PyJsonFriendly-19.11.0.dist-info/METADATA
PyJsonFriendly-19.11.0.dist-info/WHEEL
PyJsonFriendly-19.11.0.dist-info/top_level.txt
PyJsonFriendly-19.11.0.dist-info/RECORD
