Metadata-Version: 2.1
Name: PyJsonFriendly
Version: 19.11.0
Summary: UNKNOWN
Home-page: https://github.com/maboualidev/PyJsonFriendly
Author: Mohammad Abouali
Author-email: maboualidev@gmail.com
License: UNKNOWN
Platform: UNKNOWN
Classifier: Programming Language :: Python :: 3
Classifier: Operating System :: OS Independent
Requires-Python: >=3.7
